fesomp/__init__.py
fesomp/mesh/__init__.py
fesomp/mesh/geometry.py
fesomp/mesh/mesh.py
fesomp/mesh/spatial.py
fesomp/mesh/topology.py
fesomp/mesh/readers/__init__.py
fesomp/mesh/readers/ascii.py
fesomp/mesh/readers/base.py
fesomp/mesh/readers/netcdf.py
fesomp/plotting/__init__.py
fesomp/plotting/plot.py
fesomp/plotting/regrid.py
fesomp/plotting/transect.py
fesomp-0.1.0.dist-info/METADATA
fesomp-0.1.0.dist-info/WHEEL
fesomp-0.1.0.dist-info/top_level.txt
fesomp-0.1.0.dist-info/RECORD
