Metadata-Version: 2.4
Name: fesomp
Version: 0.1.0
Summary: A Python library for working with FESOM2 unstructured ocean model data
Author: nkolduno
License: MIT
Project-URL: Homepage, https://github.com/nkolduno/fesomp
Project-URL: Issues, https://github.com/nkolduno/fesomp/issues
Classifier: Development Status :: 3 - Alpha
Classifier: Intended Audience :: Science/Research
Classifier: License :: OSI Approved :: MIT License
Classifier: Operating System :: OS Independent
Classifier: Programming Language :: Python :: 3
Classifier: Programming Language :: Python :: 3.10
Classifier: Programming Language :: Python :: 3.11
Classifier: Programming Language :: Python :: 3.12
Classifier: Topic :: Scientific/Engineering :: Atmospheric Science
Classifier: Topic :: Scientific/Engineering :: Physics
Requires-Python: >=3.10
Requires-Dist: numpy>=1.20
Requires-Dist: scipy>=1.7
Requires-Dist: xarray>=0.19
Requires-Dist: pandas>=1.3
Requires-Dist: netCDF4>=1.5
Requires-Dist: matplotlib>=3.5
Requires-Dist: cartopy>=0.20
Provides-Extra: dev
Requires-Dist: pytest>=7.0; extra == "dev"
Requires-Dist: pytest-cov; extra == "dev"
Requires-Dist: hypothesis; extra == "dev"
Provides-Extra: geo
Requires-Dist: shapely>=2.0; extra == "geo"
